pipeek/__init__.py
pipeek/__main__.py
pipeek/main.py
pipeek-0.1.1.dist-info/licenses/LICENSE
pipeek-0.1.1.dist-info/METADATA
pipeek-0.1.1.dist-info/WHEEL
pipeek-0.1.1.dist-info/entry_points.txt
pipeek-0.1.1.dist-info/top_level.txt
pipeek-0.1.1.dist-info/RECORD
