Metadata-Version: 2.4
Name: pipeek
Version: 0.1.1
Summary: A search tool for compressed and uncompressed files.
Author-email: Danilo Patrial <danilopatriali@gmail.com>
License-Expression: MIT
Project-URL: Homepage, https://github.com/danilopatrial/pipeek
Classifier: Programming Language :: Python :: 3
Requires-Python: >=3.8
License-File: LICENSE
Requires-Dist: colorama
Requires-Dist: click
Requires-Dist: platformdirs
Dynamic: license-file
